<persistence xmlns="http://java.sun.com/xml/ns/persistence"
             xmlns:xsi="http://www.w3.org/2001/XMLSchema-instance"
             xsi:schemaLocation="http://java.sun.com/xml/ns/persistence http://java.sun.com/xml/ns/persistence/persistence_1_0.xsd"
             version="1.0">

    <persistence-unit name="persistence-unit" transaction-type="RESOURCE_LOCAL">
        <class>com.gl.busk.domain.BusGroup</class>
        <class>com.gl.busk.domain.BusLine</class>
        <class>com.gl.busk.domain.BusStop</class>
        <class>com.gl.busk.domain.Coordenate</class>
        <class>com.gl.busk.domain.Route</class>
        <properties>
            <property name="hibernate.hbm2ddl.auto" value="create-drop"/>
        </properties>
    </persistence-unit>

</persistence>